{"name": "Command Tower", "quantity": 1, "mana_cost": "", "cmc": 0.0, "type_line": "Land", "oracle_text": "{T}: Add one mana of any color in your commander's color identity.", "keywords": [], "legalities": {"standard": "not_legal", "future": "not_legal", "historic": "legal", "timeless": "legal", "gladiator": "legal", "pioneer": "legal", "modern": "legal", "legacy": "legal", "pauper": "legal", "vintage": "legal", "penny": "not_legal", "commander": "legal", "oathbreaker": "legal", "standardbrawl": "legal", "brawl": "legal", "alchemy": "legal", "paupercommander": "legal", "duel": "legal", "oldschool": "not_legal", "premodern": "not_legal", "predh": "not_legal"}, "image_uris": {"small": "https://cards.scryfall.io/small/front/4/d/4d51a621-be31-4b74-8e0b-3958180a8bc5.jpg?1771424570", "normal": "https://cards.scryfall.io/normal/front/4/d/4d51a621-be31-4b74-8e0b-3958180a8bc5.jpg?1771424570", "large": "https://cards.scryfall.io/large/front/4/d/4d51a621-be31-4b74-8e0b-3958180a8bc5.jpg?1771424570", "png": "https://cards.scryfall.io/png/front/4/d/4d51a621-be31-4b74-8e0b-3958180a8bc5.png?1771424570", "art_crop": "https://cards.scryfall.io/art_crop/front/4/d/4d51a621-be31-4b74-8e0b-3958180a8bc5.jpg?1771424570", "border_crop": "https://cards.scryfall.io/border_crop/front/4/d/4d51a621-be31-4b74-8e0b-3958180a8bc5.jpg?1771424570"}, "promo_types": ["universesbeyond"], "frame_effects": [], "border_color": "black", "games": ["paper", "arena", "mtgo"]}