{"name": "Tibalt's Trickery", "quantity": 1, "mana_cost": "{1}{R}", "cmc": 2.0, "type_line": "Instant", "oracle_text": "Counter target spell. Choose 1, 2, or 3 at random. Its controller mills that many cards, then exiles cards from the top of their library until they exile a nonland card with a different name than that spell. They may cast that card without paying its mana cost. Then they put the exiled cards on the bottom of their library in a random order.", "keywords": ["Mill"], "legalities": {"standard": "not_legal", "future": "not_legal", "historic": "banned", "timeless": "restricted", "gladiator": "legal", "pioneer": "legal", "modern": "banned", "legacy": "legal", "pauper": "not_legal", "vintage": "legal", "penny": "legal", "commander": "legal", "oathbreaker": "legal", "standardbrawl": "not_legal", "brawl": "legal", "alchemy": "not_legal", "paupercommander": "not_legal", "duel": "legal", "oldschool": "not_legal", "premodern": "not_legal", "predh": "not_legal"}, "image_uris": {"small": "https://cards.scryfall.io/small/front/d/d/dd921e27-3e08-438c-bec2-723226d35175.jpg?1701989318", "normal": "https://cards.scryfall.io/normal/front/d/d/dd921e27-3e08-438c-bec2-723226d35175.jpg?1701989318", "large": "https://cards.scryfall.io/large/front/d/d/dd921e27-3e08-438c-bec2-723226d35175.jpg?1701989318", "png": "https://cards.scryfall.io/png/front/d/d/dd921e27-3e08-438c-bec2-723226d35175.png?1701989318", "art_crop": "https://cards.scryfall.io/art_crop/front/d/d/dd921e27-3e08-438c-bec2-723226d35175.jpg?1701989318", "border_crop": "https://cards.scryfall.io/border_crop/front/d/d/dd921e27-3e08-438c-bec2-723226d35175.jpg?1701989318"}, "promo_types": [], "frame_effects": [], "border_color": "black", "games": ["arena", "paper", "mtgo"]}